{"_type":"export","__export_format":4,"__export_date":"2024-03-22T18:40:53.819Z","__export_source":"insomnia.desktop.app:v2022.7.5","resources":[{"_id":"req_cc7cf5c2b85841e3a339ce792e42bf7e","parentId":"wrk_92e863e4021049178340991bd9cdc9ef","modified":1711132641978,"created":1711132641978,"url":"","name":"New Request","description":"","method":"GET","body":{},"parameters":[],"headers":[],"authentication":{},"metaSortKey":-1711132641978,"isPrivate":false,"settingStoreCookies":true,"settingSendCookies":true,"settingDisableRenderRequestBody":false,"settingEncodeUrl":true,"settingRebuildPath":true,"settingFollowRedirects":"global","_type":"request"},{"_id":"wrk_92e863e4021049178340991bd9cdc9ef","parentId":null,"modified":1674483403822,"created":1674483403822,"name":"New Document","description":"","scope":"design","_type":"workspace"},{"_id":"req_ddac0270a92849c9aebe7ce7c585396d","parentId":"wrk_92e863e4021049178340991bd9cdc9ef","modified":1711132639129,"created":1711131675448,"url":"127.0.0.1/api/lista/exercicio3","name":"exercicio3","description":"","method":"GET","body":{"mimeType":"application/json","text":"{\n\t\"idade\":\"28\"\n}"},"parameters":[],"headers":[{"name":"Content-Type","value":"application/json"}],"authentication":{},"metaSortKey":-1711131675448,"isPrivate":false,"settingStoreCookies":true,"settingSendCookies":true,"settingDisableRenderRequestBody":false,"settingEncodeUrl":true,"settingRebuildPath":true,"settingFollowRedirects":"global","_type":"request"},{"_id":"req_aa629c841edd43829f9c03976d2d7edd","parentId":"wrk_92e863e4021049178340991bd9cdc9ef","modified":1711132185084,"created":1711131124441,"url":"127.0.0.1/api/lista/exercicio19","name":"exercicio17","description":"","method":"GET","body":{"mimeType":"application/json","text":"{\n\t\"numero1\":\"10\",\n\t\"numero2\":\"10\"\n\t\n}"},"parameters":[],"headers":[{"name":"Content-Type","value":"application/json"}],"authentication":{},"metaSortKey":-1711131124441,"isPrivate":false,"settingStoreCookies":true,"settingSendCookies":true,"settingDisableRenderRequestBody":false,"settingEncodeUrl":true,"settingRebuildPath":true,"settingFollowRedirects":"global","_type":"request"},{"_id":"req_af080a558e1a449cb06ec3b717f4e554","parentId":"wrk_92e863e4021049178340991bd9cdc9ef","modified":1711131136032,"created":1711129704750,"url":"127.0.0.1/api/lista/exercicio16","name":"exercicio16","description":"","method":"GET","body":{"mimeType":"application/json","text":"{\n\t\"numero1\":\"100\",\n\t\"numero2\":\"70\"\n\t\n}"},"parameters":[],"headers":[{"name":"Content-Type","value":"application/json"}],"authentication":{},"metaSortKey":-1711129704750,"isPrivate":false,"settingStoreCookies":true,"settingSendCookies":true,"settingDisableRenderRequestBody":false,"settingEncodeUrl":true,"settingRebuildPath":true,"settingFollowRedirects":"global","_type":"request"},{"_id":"req_a5d9a38f41a946ebb0e414f8d0c6085b","parentId":"wrk_92e863e4021049178340991bd9cdc9ef","modified":1711129701345,"created":1711125463438,"url":"127.0.0.1/api/lista/exercicio14","name":"exercicio14","description":"","method":"GET","body":{"mimeType":"application/json","text":"{\n\t\"idade\":\"17\"\n}"},"parameters":[],"headers":[{"name":"Content-Type","value":"application/json"}],"authentication":{},"metaSortKey":-1711125463438,"isPrivate":false,"settingStoreCookies":true,"settingSendCookies":true,"settingDisableRenderRequestBody":false,"settingEncodeUrl":true,"settingRebuildPath":true,"settingFollowRedirects":"global","_type":"request"},{"_id":"req_cbdecf3dcd6c4202ad85c0bc625862c1","parentId":"wrk_92e863e4021049178340991bd9cdc9ef","modified":1711125473066,"created":1711125280361,"url":"127.0.0.1/api/lista/exercicio6","name":"exercicio6","description":"","method":"GET","body":{"mimeType":"application/json","text":"{\n\t\"numero\":\"5381\"\n\t\n}"},"parameters":[],"headers":[{"name":"Content-Type","value":"application/json"}],"authentication":{},"metaSortKey":-1711125280361,"isPrivate":false,"settingStoreCookies":true,"settingSendCookies":true,"settingDisableRenderRequestBody":false,"settingEncodeUrl":true,"settingRebuildPath":true,"settingFollowRedirects":"global","_type":"request"},{"_id":"req_e29b12a5715a4aefb1d408f930c289b1","parentId":"wrk_92e863e4021049178340991bd9cdc9ef","modified":1711125306741,"created":1711125191436,"url":"127.0.0.1/api/lista/exercicio8","name":"exercicio8","description":"","method":"GET","body":{"mimeType":"application/json","text":"{\n\t\"numero\":\"2\"\n\t\n}"},"parameters":[],"headers":[{"name":"Content-Type","value":"application/json"}],"authentication":{},"metaSortKey":-1711125191436,"isPrivate":false,"settingStoreCookies":true,"settingSendCookies":true,"settingDisableRenderRequestBody":false,"settingEncodeUrl":true,"settingRebuildPath":true,"settingFollowRedirects":"global","_type":"request"},{"_id":"req_87b61182ba904f21943ba90ce9cc1585","parentId":"wrk_92e863e4021049178340991bd9cdc9ef","modified":1711126439313,"created":1711125113767,"url":"127.0.0.1/api/lista/exercicio9","name":"exercicio9","description":"","method":"GET","body":{"mimeType":"application/json","text":"{\n\t\"idade\":\"12\"\n\t\n}"},"parameters":[],"headers":[{"name":"Content-Type","value":"application/json"}],"authentication":{},"metaSortKey":-1711125113767,"isPrivate":false,"settingStoreCookies":true,"settingSendCookies":true,"settingDisableRenderRequestBody":false,"settingEncodeUrl":true,"settingRebuildPath":true,"settingFollowRedirects":"global","_type":"request"},{"_id":"req_8a696cf6b6bf465b88114e50342d31d3","parentId":"wrk_92e863e4021049178340991bd9cdc9ef","modified":1711126725100,"created":1711116681811,"url":"127.0.0.1/api/lista/exercicio11","name":"exercicio11","description":"","method":"GET","body":{"mimeType":"application/json","text":"{\n\t\"numero\":\"1000\"\n}"},"parameters":[],"headers":[{"name":"Content-Type","value":"application/json"}],"authentication":{},"metaSortKey":-1711116681811,"isPrivate":false,"settingStoreCookies":true,"settingSendCookies":true,"settingDisableRenderRequestBody":false,"settingEncodeUrl":true,"settingRebuildPath":true,"settingFollowRedirects":"global","_type":"request"},{"_id":"req_c53646ad66e14a3f8357076487600083","parentId":"wrk_92e863e4021049178340991bd9cdc9ef","modified":1710518255602,"created":1710518190351,"url":"127.0.0.1/api/exercicio17","name":"17","description":"","method":"GET","body":{"mimeType":"application/json","text":"{\n\t\"preço\":\"300\",\n\t\"quanto\":\"40\"\n\t\n\t\n\t\n}"},"parameters":[],"headers":[{"name":"Content-Type","value":"application/json"}],"authentication":{},"metaSortKey":-1710518190351,"isPrivate":false,"settingStoreCookies":true,"settingSendCookies":true,"settingDisableRenderRequestBody":false,"settingEncodeUrl":true,"settingRebuildPath":true,"settingFollowRedirects":"global","_type":"request"},{"_id":"req_9c42a8e5db2147179d60f0af6b91699c","parentId":"wrk_92e863e4021049178340991bd9cdc9ef","modified":1710518196792,"created":1710518149526,"url":"127.0.0.1/api/exercicio16","name":"16","description":"","method":"GET","body":{"mimeType":"application/json","text":"{\n\t\"dias\":\"10\"\n\t\n\t\n\t\n}"},"parameters":[],"headers":[{"name":"Content-Type","value":"application/json"}],"authentication":{},"metaSortKey":-1710518149526,"isPrivate":false,"settingStoreCookies":true,"settingSendCookies":true,"settingDisableRenderRequestBody":false,"settingEncodeUrl":true,"settingRebuildPath":true,"settingFollowRedirects":"global","_type":"request"},{"_id":"req_c2373735eceb46b6a3acd1fdf3333a90","parentId":"wrk_92e863e4021049178340991bd9cdc9ef","modified":1710518156370,"created":1710518094056,"url":"127.0.0.1/api/exercicio15","name":"15","description":"","method":"GET","body":{"mimeType":"application/json","text":"{\n\t\"valor\":\"200\",\n\t\"comissao\":\"30\"\n\t\n\t\n}"},"parameters":[],"headers":[{"name":"Content-Type","value":"application/json"}],"authentication":{},"metaSortKey":-1710518094056,"isPrivate":false,"settingStoreCookies":true,"settingSendCookies":true,"settingDisableRenderRequestBody":false,"settingEncodeUrl":true,"settingRebuildPath":true,"settingFollowRedirects":"global","_type":"request"},{"_id":"req_9f4fe80c54154632ad6ed4fd5e7f4512","parentId":"wrk_92e863e4021049178340991bd9cdc9ef","modified":1710518100360,"created":1710518054647,"url":"127.0.0.1/api/exercicio14","name":"14","description":"","method":"GET","body":{"mimeType":"application/json","text":"{\n\t\"valor\":\"200\"\n\t\n\t\n\t\n}"},"parameters":[],"headers":[{"name":"Content-Type","value":"application/json"}],"authentication":{},"metaSortKey":-1710518054647,"isPrivate":false,"settingStoreCookies":true,"settingSendCookies":true,"settingDisableRenderRequestBody":false,"settingEncodeUrl":true,"settingRebuildPath":true,"settingFollowRedirects":"global","_type":"request"},{"_id":"req_dce8ad7344f24cd0ac7ee3e33361f08b","parentId":"wrk_92e863e4021049178340991bd9cdc9ef","modified":1710518061316,"created":1710517987474,"url":"127.0.0.1/api/exercicio13","name":"13","description":"","method":"GET","body":{"mimeType":"application/json","text":"{\n\t\"salario\":\"1200\",\n\t\"aumento\":\"500\"\n\t\n\t\n}"},"parameters":[],"headers":[{"name":"Content-Type","value":"application/json"}],"authentication":{},"metaSortKey":-1710517987474,"isPrivate":false,"settingStoreCookies":true,"settingSendCookies":true,"settingDisableRenderRequestBody":false,"settingEncodeUrl":true,"settingRebuildPath":true,"settingFollowRedirects":"global","_type":"request"},{"_id":"req_431e5598c87e4c3ba2539e19e2f72f6a","parentId":"wrk_92e863e4021049178340991bd9cdc9ef","modified":1710517994132,"created":1710517923144,"url":"127.0.0.1/api/exercicio12","name":"12","description":"","method":"GET","body":{"mimeType":"application/json","text":"{\n\t\"compra\":\"200\",\n\t\"desconto\":\"30\"\n\t\n\t\n}"},"parameters":[],"headers":[{"name":"Content-Type","value":"application/json"}],"authentication":{},"metaSortKey":-1710517923144,"isPrivate":false,"settingStoreCookies":true,"settingSendCookies":true,"settingDisableRenderRequestBody":false,"settingEncodeUrl":true,"settingRebuildPath":true,"settingFollowRedirects":"global","_type":"request"},{"_id":"req_18c3390ca74546e699990ff671bff4d9","parentId":"wrk_92e863e4021049178340991bd9cdc9ef","modified":1710517931616,"created":1710517860505,"url":"127.0.0.1/api/exercicio11","name":"11","description":"","method":"GET","body":{"mimeType":"application/json","text":"{\n\t\"base\":\"10\",\n\t\"altura\":\"20\"\n\t\n\t\n\t\n}"},"parameters":[],"headers":[{"name":"Content-Type","value":"application/json"}],"authentication":{},"metaSortKey":-1710517860505,"isPrivate":false,"settingStoreCookies":true,"settingSendCookies":true,"settingDisableRenderRequestBody":false,"settingEncodeUrl":true,"settingRebuildPath":true,"settingFollowRedirects":"global","_type":"request"},{"_id":"req_4a54ff76342f468aa9afa9303c60ae2d","parentId":"wrk_92e863e4021049178340991bd9cdc9ef","modified":1710517866986,"created":1710517803120,"url":"127.0.0.1/api/exercicio10","name":"10","description":"","method":"GET","body":{"mimeType":"application/json","text":"{\n\t\"primeiroNumero\":\"200\"\n\t\n\t\n}"},"parameters":[],"headers":[{"name":"Content-Type","value":"application/json"}],"authentication":{},"metaSortKey":-1710517803120,"isPrivate":false,"settingStoreCookies":true,"settingSendCookies":true,"settingDisableRenderRequestBody":false,"settingEncodeUrl":true,"settingRebuildPath":true,"settingFollowRedirects":"global","_type":"request"},{"_id":"req_ea77633b2d024ccaae1348c4e7c27c0a","parentId":"wrk_92e863e4021049178340991bd9cdc9ef","modified":1710517809714,"created":1710517728157,"url":"127.0.0.1/api/exercicio9","name":"9","description":"","method":"GET","body":{"mimeType":"application/json","text":"{\n\t\"primeiroNumero\":\"100\",\n\t\"segundoNumero\":\"80\"\n\t\n\t\n\t\n\t\n}"},"parameters":[],"headers":[{"name":"Content-Type","value":"application/json"}],"authentication":{},"metaSortKey":-1710517728157,"isPrivate":false,"settingStoreCookies":true,"settingSendCookies":true,"settingDisableRenderRequestBody":false,"settingEncodeUrl":true,"settingRebuildPath":true,"settingFollowRedirects":"global","_type":"request"},{"_id":"req_55a7015179f846609e88d8c6a158b891","parentId":"wrk_92e863e4021049178340991bd9cdc9ef","modified":1710517736659,"created":1710517572468,"url":"127.0.0.1/api/exercicio8","name":"8","description":"","method":"GET","body":{"mimeType":"application/json","text":"{\n\t\"primeiraNota\":\"10\",\n\t\"segundaNota\":\"9\",\n\t\"terceiraNota\":\"8\",\n\t\"quartaNota\":\"7\",\n\t\"quintaNota\":\"6\"\n\t\n\t\n\t\n}"},"parameters":[],"headers":[{"name":"Content-Type","value":"application/json"}],"authentication":{},"metaSortKey":-1710517572468,"isPrivate":false,"settingStoreCookies":true,"settingSendCookies":true,"settingDisableRenderRequestBody":false,"settingEncodeUrl":true,"settingRebuildPath":true,"settingFollowRedirects":"global","_type":"request"},{"_id":"req_c4bb6337955745ef922f8aeb20c877d9","parentId":"wrk_92e863e4021049178340991bd9cdc9ef","modified":1710517579810,"created":1710517495693,"url":"127.0.0.1/api/exercicio7","name":"7","description":"","method":"GET","body":{"mimeType":"application/json","text":"{\n\t\"primeiroNumero\":\"30\",\n\t\"segundoNumero\":\"40\"\n\t\n\t\n}"},"parameters":[],"headers":[{"name":"Content-Type","value":"application/json"}],"authentication":{},"metaSortKey":-1710517495693,"isPrivate":false,"settingStoreCookies":true,"settingSendCookies":true,"settingDisableRenderRequestBody":false,"settingEncodeUrl":true,"settingRebuildPath":true,"settingFollowRedirects":"global","_type":"request"},{"_id":"req_aefe682392ad4ebd83d4ad1aa96e1c2c","parentId":"wrk_92e863e4021049178340991bd9cdc9ef","modified":1710517502716,"created":1710517429443,"url":"127.0.0.1/api/exercicio6","name":"6","description":"","method":"GET","body":{"mimeType":"application/json","text":"{\n\t\"primeiroNumero\":\"50\",\n\t\"segundoNumero\":\"100\"\n\t\n\t\n\t\n}"},"parameters":[],"headers":[{"name":"Content-Type","value":"application/json"}],"authentication":{},"metaSortKey":-1710517429443,"isPrivate":false,"settingStoreCookies":true,"settingSendCookies":true,"settingDisableRenderRequestBody":false,"settingEncodeUrl":true,"settingRebuildPath":true,"settingFollowRedirects":"global","_type":"request"},{"_id":"req_23c373bc31f946f1ac6a94ce0f48838b","parentId":"wrk_92e863e4021049178340991bd9cdc9ef","modified":1710517438571,"created":1710517337928,"url":"127.0.0.1/api/exercicio5","name":"5","description":"","method":"GET","body":{"mimeType":"application/json","text":"{\n\t\"primeiroNumero\":\"10\",\n\t\"segundoNumero\":\"30\",\n\t\"terceiroNumero\":\"50\"\n\t\n\t\n}"},"parameters":[],"headers":[{"name":"Content-Type","value":"application/json"}],"authentication":{},"metaSortKey":-1710517337928,"isPrivate":false,"settingStoreCookies":true,"settingSendCookies":true,"settingDisableRenderRequestBody":false,"settingEncodeUrl":true,"settingRebuildPath":true,"settingFollowRedirects":"global","_type":"request"},{"_id":"req_021b464ced434f1391b23cd5b15711ec","parentId":"wrk_92e863e4021049178340991bd9cdc9ef","modified":1710517345196,"created":1710517264616,"url":"127.0.0.1/api/exercicio4","name":"4","description":"","method":"GET","body":{"mimeType":"application/json","text":"{\n\t\"primeiroNumero\":\"10\",\n\t\"segundoNumero\":\"30\"\n\t\n}"},"parameters":[],"headers":[{"name":"Content-Type","value":"application/json"}],"authentication":{},"metaSortKey":-1710517264616,"isPrivate":false,"settingStoreCookies":true,"settingSendCookies":true,"settingDisableRenderRequestBody":false,"settingEncodeUrl":true,"settingRebuildPath":true,"settingFollowRedirects":"global","_type":"request"},{"_id":"req_0ca47b5fd8bb41b1baec1e77201bdcc1","parentId":"wrk_92e863e4021049178340991bd9cdc9ef","modified":1710517272689,"created":1710517167077,"url":"127.0.0.1/api/exercicio3","name":"3","description":"","method":"GET","body":{"mimeType":"application/json","text":"{\n\t\"nome\":\"Bruno\",\n\t\"ano\":\"2006\",\n\t\"cidade\":\"Presedente Epitacio\"\n\t\n\t\n}"},"parameters":[],"headers":[{"name":"Content-Type","value":"application/json"}],"authentication":{},"metaSortKey":-1710517167077,"isPrivate":false,"settingStoreCookies":true,"settingSendCookies":true,"settingDisableRenderRequestBody":false,"settingEncodeUrl":true,"settingRebuildPath":true,"settingFollowRedirects":"global","_type":"request"},{"_id":"req_3b573af6ac4441f285e5bf0ff49d7b4e","parentId":"wrk_92e863e4021049178340991bd9cdc9ef","modified":1710517174500,"created":1710517089952,"url":"127.0.0.1/api/exercicio2","name":"2","description":"","method":"GET","body":{"mimeType":"application/json","text":"{\n\t\"nome\":\"bruno\",\n\t\"idade\":\"17\"\n\t\n\t\n}"},"parameters":[],"headers":[{"name":"Content-Type","value":"application/json"}],"authentication":{},"metaSortKey":-1710517089952,"isPrivate":false,"settingStoreCookies":true,"settingSendCookies":true,"settingDisableRenderRequestBody":false,"settingEncodeUrl":true,"settingRebuildPath":true,"settingFollowRedirects":"global","_type":"request"},{"_id":"req_5d389d098fdb4343b36b9de3940937cc","parentId":"wrk_92e863e4021049178340991bd9cdc9ef","modified":1710517096902,"created":1710516967395,"url":"127.0.0.1/api/exercicio1","name":"1","description":"","method":"GET","body":{"mimeType":"application/json","text":"{\n\t\"nome\":\"Bruno\"\n\t\n\t\n}"},"parameters":[],"headers":[{"name":"Content-Type","value":"application/json"}],"authentication":{},"metaSortKey":-1710516967395,"isPrivate":false,"settingStoreCookies":true,"settingSendCookies":true,"settingDisableRenderRequestBody":false,"settingEncodeUrl":true,"settingRebuildPath":true,"settingFollowRedirects":"global","_type":"request"},{"_id":"req_643569000f7e46a8a79b33af5749b5a9","parentId":"wrk_92e863e4021049178340991bd9cdc9ef","modified":1674483403831,"created":1674483403831,"url":"","name":"New Request","description":"","method":"GET","body":{},"parameters":[],"headers":[],"authentication":{},"metaSortKey":-1674483403831,"isPrivate":false,"settingStoreCookies":true,"settingSendCookies":true,"settingDisableRenderRequestBody":false,"settingEncodeUrl":true,"settingRebuildPath":true,"settingFollowRedirects":"global","_type":"request"},{"_id":"env_345c9bd1a2912c8ecdd515437a154274cef216ec","parentId":"wrk_92e863e4021049178340991bd9cdc9ef","modified":1674483403826,"created":1674483403826,"name":"Base Environment","data":{},"dataPropertyOrder":null,"color":null,"isPrivate":false,"metaSortKey":1674483403826,"_type":"environment"},{"_id":"jar_345c9bd1a2912c8ecdd515437a154274cef216ec","parentId":"wrk_92e863e4021049178340991bd9cdc9ef","modified":1674483403827,"created":1674483403827,"name":"Default Jar","cookies":[],"_type":"cookie_jar"},{"_id":"spc_3f78eb2013b94aaf81b3cf226fcc46ae","parentId":"wrk_92e863e4021049178340991bd9cdc9ef","modified":1710511338093,"created":1674483403822,"fileName":"New Document","contents":"","contentType":"yaml","_type":"api_spec"},{"_id":"uts_1380377451c2487d95e3939bbc8a822b","parentId":"wrk_92e863e4021049178340991bd9cdc9ef","modified":1674483403833,"created":1674483403833,"name":"Example Test Suite","_type":"unit_test_suite"}]}